markitdown_pro/__init__.py
markitdown_pro/conversion_pipeline.py
markitdown_pro/common/__init__.py
markitdown_pro/common/isolated_worker.py
markitdown_pro/common/logger.py
markitdown_pro/common/schemas.py
markitdown_pro/common/utils.py
markitdown_pro/converters/__init__.py
markitdown_pro/converters/azure_doc_intel_wrapper.py
markitdown_pro/converters/azure_speech_wrapper.py
markitdown_pro/converters/base.py
markitdown_pro/converters/gpt_vision_wrapper.py
markitdown_pro/converters/markitdown_wrapper.py
markitdown_pro/converters/pymupdf_wrapper.py
markitdown_pro/converters/tabular_wrapper.py
markitdown_pro/converters/unstructured_wrapper.py
markitdown_pro/converters/youtube_wrapper.py
markitdown_pro/handlers/__init__.py
markitdown_pro/handlers/audio_handler.py
markitdown_pro/handlers/base_handler.py
markitdown_pro/handlers/email_handler.py
markitdown_pro/handlers/epub_handler.py
markitdown_pro/handlers/image_handler.py
markitdown_pro/handlers/ipynb_handler.py
markitdown_pro/handlers/markitdown_handler.py
markitdown_pro/handlers/markup_handler.py
markitdown_pro/handlers/office_handler.py
markitdown_pro/handlers/pdf_handler.py
markitdown_pro/handlers/pst_handler.py
markitdown_pro/handlers/tabular_handler.py
markitdown_pro/handlers/text_handler.py
markitdown_pro/services/__init__.py
markitdown_pro/services/azure_doc_intelligence.py
markitdown_pro/services/azure_speech.py
markitdown_pro/services/openai_services.py
markitdown_pro-1.3.7.dist-info/METADATA
markitdown_pro-1.3.7.dist-info/WHEEL
markitdown_pro-1.3.7.dist-info/top_level.txt
markitdown_pro-1.3.7.dist-info/RECORD
