Metadata-Version: 2.4
Name: markitdown-pro
Version: 1.3.7
Summary: A package that converts almost any file format to Markdown.
Author: Developer
Classifier: Programming Language :: Python :: 3
Classifier: License :: OSI Approved :: MIT License
Classifier: Operating System :: OS Independent
Requires-Python: >=3.12.2
Requires-Dist: aiohttp
Requires-Dist: requests
Requires-Dist: httpx
Requires-Dist: python-dotenv
Requires-Dist: ffmpeg
Requires-Dist: pandoc
Requires-Dist: PyMuPDF
Requires-Dist: whisper
Requires-Dist: markitdown[all]
Requires-Dist: huggingface_hub[hf_xet]
Requires-Dist: unstructured[all-docs]
Requires-Dist: langchain-core==0.3.74
Requires-Dist: langchain-openai==0.3.29
Requires-Dist: azure-ai-documentintelligence==1.0.2
Requires-Dist: azure-cognitiveservices-speech==1.42.0
Requires-Dist: chardet==5.2.0
Requires-Dist: nbformat
Requires-Dist: youtube-transcript-api
Requires-Dist: tabulate
Requires-Dist: ebooklib
Requires-Dist: beautifulsoup4
Requires-Dist: cairosvg
Requires-Dist: pillow_heif
Dynamic: author
Dynamic: classifier
Dynamic: description
Dynamic: description-content-type
Dynamic: requires-dist
Dynamic: requires-python
Dynamic: summary
